platform_api_python_client/__init__.py
platform_api_python_client/api_client.py
platform_api_python_client/api_response.py
platform_api_python_client/configuration.py
platform_api_python_client/exceptions.py
platform_api_python_client/py.typed
platform_api_python_client/rest.py
platform_api_python_client/api/__init__.py
platform_api_python_client/api/external_api.py
platform_api_python_client/models/__init__.py
platform_api_python_client/models/api_key_request.py
platform_api_python_client/models/api_key_response.py
platform_api_python_client/models/c_serve_recipe_perf.py
platform_api_python_client/models/c_serve_recipe_response.py
platform_api_python_client/models/c_serve_v2_recipe.py
platform_api_python_client/models/create_c_serve_v2_deployment_request.py
platform_api_python_client/models/create_c_serve_v2_deployment_response.py
platform_api_python_client/models/create_c_serve_v3_deployment_request.py
platform_api_python_client/models/create_c_serve_v3_deployment_response.py
platform_api_python_client/models/create_compute_deployment_request.py
platform_api_python_client/models/create_compute_deployment_response.py
platform_api_python_client/models/create_inference_deployment_request.py
platform_api_python_client/models/create_inference_deployment_response.py
platform_api_python_client/models/create_inference_v3_deployment_request.py
platform_api_python_client/models/create_organization_request.py
platform_api_python_client/models/create_organization_response.py
platform_api_python_client/models/create_rag_deployment_request.py
platform_api_python_client/models/create_rag_deployment_response.py
platform_api_python_client/models/create_url_request.py
platform_api_python_client/models/create_url_response.py
platform_api_python_client/models/credits_response.py
platform_api_python_client/models/daily_bill_response.py
platform_api_python_client/models/deployment_response.py
platform_api_python_client/models/deployment_status.py
platform_api_python_client-4.1.9.dist-info/METADATA
platform_api_python_client-4.1.9.dist-info/WHEEL
platform_api_python_client-4.1.9.dist-info/top_level.txt
platform_api_python_client-4.1.9.dist-info/RECORD
